discover_utils/__init__.py
discover_utils/data/__init__.py
discover_utils/data/annotation.py
discover_utils/data/data.py
discover_utils/data/static.py
discover_utils/data/stream.py
discover_utils/data/file_reader/__init__.py
discover_utils/data/file_reader/video/__init__.py
discover_utils/data/file_reader/video/decord.py
discover_utils/data/file_reader/video/decord_batch.py
discover_utils/data/file_reader/video/imageio.py
discover_utils/data/file_reader/video/moviepy.py
discover_utils/data/file_reader/video/pyav.py
discover_utils/data/handler/__init__.py
discover_utils/data/handler/file_handler.py
discover_utils/data/handler/ihandler.py
discover_utils/data/handler/nova_db_handler.py
discover_utils/data/handler/request_handler.py
discover_utils/data/handler/url_handler.py
discover_utils/data/provider/__init__.py
discover_utils/data/provider/data_manager.py
discover_utils/data/provider/dataset_iterator.py
discover_utils/interfaces/__init__.py
discover_utils/interfaces/server_module.py
discover_utils/scripts/__init__.py
discover_utils/scripts/parsers.py
discover_utils/scripts/process.py
discover_utils/scripts/train.py
discover_utils/utils/__init__.py
discover_utils/utils/anno_utils.py
discover_utils/utils/cache_utils.py
discover_utils/utils/json_utils.py
discover_utils/utils/log_utils.py
discover_utils/utils/path_utils.py
discover_utils/utils/request_utils.py
discover_utils/utils/ssi_data_types.py
discover_utils/utils/ssi_xml_utils.py
discover_utils/utils/stream_utils.py
discover_utils/utils/string_utils.py
discover_utils/utils/type_definitions.py
docs/docsource/conf.py
hcai_discover_utils-1.0.10.dist-info/METADATA
hcai_discover_utils-1.0.10.dist-info/WHEEL
hcai_discover_utils-1.0.10.dist-info/entry_points.txt
hcai_discover_utils-1.0.10.dist-info/top_level.txt
hcai_discover_utils-1.0.10.dist-info/RECORD
